yoakecli/__init__.py
yoakecli/player.py
yoakecli/simpleRequest.py
yoakecli/styling.py
yoakecli/yoakeCLI.py
yoakecli-0.0.2.dist-info/LICENSE
yoakecli-0.0.2.dist-info/METADATA
yoakecli-0.0.2.dist-info/WHEEL
yoakecli-0.0.2.dist-info/entry_points.txt
yoakecli-0.0.2.dist-info/top_level.txt
yoakecli-0.0.2.dist-info/RECORD
