Metadata-Version: 2.1
Name: yoakecli
Version: 0.0.2
Summary: Light-weight CLI tool for yoake.moe
Author: Yoake
Author-email: zedovblack@gmail.com
Classifier: Programming Language :: Python :: 3
Classifier: License :: OSI Approved :: MIT License
Classifier: Operating System :: Microsoft :: Windows
Classifier: Operating System :: Android
Classifier: Natural Language :: Vietnamese
License-File: LICENSE
